jupyter_deploy_tf_aws_ec2_ngrok/__init__.py
jupyter_deploy_tf_aws_ec2_ngrok/template.py
jupyter_deploy_tf_aws_ec2_ngrok/template/cloudinit.sh
jupyter_deploy_tf_aws_ec2_ngrok/template/docker-compose.yml
jupyter_deploy_tf_aws_ec2_ngrok/template/docker-startup.sh
jupyter_deploy_tf_aws_ec2_ngrok/template/dockerfile.jupyter
jupyter_deploy_tf_aws_ec2_ngrok/template/main.tf
jupyter_deploy_tf_aws_ec2_ngrok/template/ngrok.yml.tftpl
jupyter_deploy_tf_aws_ec2_ngrok/template/outputs.tf
jupyter_deploy_tf_aws_ec2_ngrok/template/variables.tf
jupyter_deploy_tf_aws_ec2_ngrok-0.1.0.dist-info/METADATA
jupyter_deploy_tf_aws_ec2_ngrok-0.1.0.dist-info/WHEEL
jupyter_deploy_tf_aws_ec2_ngrok-0.1.0.dist-info/entry_points.txt
jupyter_deploy_tf_aws_ec2_ngrok-0.1.0.dist-info/RECORD
