Metadata-Version: 2.4
Name: jupyter-deploy-tf-aws-ec2-ngrok
Version: 0.1.0
Author-email: Jonathan Guinegagne <jggg@amazon.com>
Requires-Python: >=3.12
